nfrapy/__init__.py
nfrapy/cli.py
nfrapy/nfrapy.py
nfrapy/nfrapy_get_ts.py
nfrapy-0.1.dist-info/AUTHORS.rst
nfrapy-0.1.dist-info/LICENSE
nfrapy-0.1.dist-info/METADATA
nfrapy-0.1.dist-info/WHEEL
nfrapy-0.1.dist-info/entry_points.txt
nfrapy-0.1.dist-info/top_level.txt
nfrapy-0.1.dist-info/RECORD
